{
  "timeZone": "Europe/London",
  "dependencies": {
    "enabledAdvancedServices": [{
      "userSymbol": "Slides",
      "serviceId": "slides",
      "version": "v1"
    }],
    "libraries": [{
      "userSymbol": "cUseful",
      "libraryId": "1EbLSESpiGkI3PYmJqWh3-rmLkYKAtCNPi1L2YCtMgo2Ut8xMThfJ41Ex",
      "version": "94"
    }, {
      "userSymbol": "cEffexApiClient",
      "libraryId": "19rhki6VDTWk4v1RDb6u1d5E-nNaQq8sXCnRnFzUpp4V4lmZ9Z6R_PP9n",
      "version": "9"
    }]
  },
  "webapp": {
    "access": "ANYONE_ANONYMOUS",
    "executeAs": "USER_DEPLOYING"
  },
  "exceptionLogging": "STACKDRIVER"
}